{
  "slug": "cska",
  "title": "CSKA",
  "client": "CSKA",
  "year": "2025 — present",
  "category": "brand",
  "description": "Sneaker customization with CSKA club branding. Limited gifts for VIPs and top management of the club — unique branded merch.",
  "stats": [],
  "coverImage": "/projects/cska/1.jpeg",
  "gallery": [
    "/projects/cska/1.jpeg",
    "/projects/cska/2.jpeg",
    "/projects/cska/3.jpeg",
    "/projects/cska/4.jpeg",
    "/projects/cska/5.jpeg",
    "/projects/cska/6.jpeg",
    "/projects/cska/7.jpeg",
    "/projects/cska/8.jpeg"
  ],
  "details": {
    "task": "Create branded sneakers with CSKA branding for VIP club gifts.",
    "solution": "Hand-painted sneakers, club branding, heat-transfer prints, DTF film, lace replacement.",
    "result": "Branded custom sneakers — a limited gift for the club's VIPs."
  }
}
